plover/__init__.py
plover/__main__.py
plover/config.py
plover/engine.py
plover/exception.py
plover/formatting.py
plover/i18n.py
plover/key_combo.py
plover/log.py
plover/misc.py
plover/orthography.py
plover/registry.py
plover/resource.py
plover/steno.py
plover/steno_dictionary.py
plover/suggestions.py
plover/translation.py
plover/assets/american_english_words.txt
plover/assets/commands.json
plover/assets/main.json
plover/assets/plover-icon.svg
plover/assets/plover.ico
plover/assets/plover.png
plover/assets/user.json
plover/command/__init__.py
plover/command/set_config.py
plover/dictionary/__init__.py
plover/dictionary/base.py
plover/dictionary/helpers.py
plover/dictionary/json_dict.py
plover/dictionary/loading_manager.py
plover/dictionary/rtfcre_dict.py
plover/dictionary/rtfcre_parse.py
plover/gui_none/__init__.py
plover/gui_none/add_translation.py
plover/gui_none/engine.py
plover/gui_none/main.py
plover/gui_qt/__init__.py
plover/gui_qt/about_dialog.py
plover/gui_qt/about_dialog_ui.py
plover/gui_qt/add_translation_dialog.py
plover/gui_qt/add_translation_dialog_ui.py
plover/gui_qt/add_translation_widget.py
plover/gui_qt/add_translation_widget_ui.py
plover/gui_qt/appearance.py
plover/gui_qt/config_file_widget_ui.py
plover/gui_qt/config_keyboard_widget_ui.py
plover/gui_qt/config_plover_hid_widget_ui.py
plover/gui_qt/config_serial_widget_ui.py
plover/gui_qt/config_window.py
plover/gui_qt/config_window_ui.py
plover/gui_qt/console_widget.py
plover/gui_qt/console_widget_ui.py
plover/gui_qt/dictionaries_widget.py
plover/gui_qt/dictionaries_widget_ui.py
plover/gui_qt/dictionary_editor.py
plover/gui_qt/dictionary_editor_ui.py
plover/gui_qt/engine.py
plover/gui_qt/info_browser.py
plover/gui_qt/log_qt.py
plover/gui_qt/lookup_dialog.py
plover/gui_qt/lookup_dialog_ui.py
plover/gui_qt/machine_options.py
plover/gui_qt/main.py
plover/gui_qt/main_window.py
plover/gui_qt/main_window_ui.py
plover/gui_qt/paper_tape.py
plover/gui_qt/paper_tape_ui.py
plover/gui_qt/plugins_manager.py
plover-5.2.0.dist-info/licenses/LICENSE.txt
plover-5.2.0.dist-info/METADATA
plover-5.2.0.dist-info/WHEEL
plover-5.2.0.dist-info/entry_points.txt
plover-5.2.0.dist-info/top_level.txt
plover-5.2.0.dist-info/zip-safe
plover-5.2.0.dist-info/RECORD
