Metadata-Version: 2.4
Name: plover
Version: 5.2.0
Summary: Open Source Stenography Software
Home-page: http://www.openstenoproject.org/
Download-URL: http://www.openstenoproject.org/plover
Author: Joshua Harlan Lifton
Author-email: joshua.harlan.lifton@gmail.com
Maintainer: Martin Koerner
Maintainer-email: info@mkrnr.com
License: GNU General Public License v2 or later (GPLv2+)
Project-URL: Changelog, https://github.com/openstenoproject/plover/blob/master/NEWS.md
Project-URL: Source Code, https://github.com/openstenoproject/plover
Project-URL: Issue Tracker, https://github.com/openstenoproject/plover/issues
Keywords: plover
Classifier: Programming Language :: Python :: 3
Classifier: Programming Language :: Python :: 3.10
Classifier: Programming Language :: Python :: 3.11
Classifier: Programming Language :: Python :: 3.12
Classifier: Programming Language :: Python :: 3.13
Classifier: Development Status :: 5 - Production/Stable
Classifier: Environment :: X11 Applications
Classifier: Environment :: MacOS X
Classifier: Environment :: Win32 (MS Windows)
Classifier: Intended Audience :: End Users/Desktop
Classifier: Natural Language :: English
Classifier: Operating System :: POSIX :: BSD
Classifier: Operating System :: POSIX :: Linux
Classifier: Operating System :: MacOS :: MacOS X
Classifier: Operating System :: Microsoft :: Windows
Classifier: Topic :: Adaptive Technologies
Classifier: Topic :: Desktop Environment
Requires-Python: >=3.10
License-File: LICENSE.txt
Requires-Dist: appdirs
Requires-Dist: appnope; "darwin" in sys_platform
Requires-Dist: hidapi
Requires-Dist: pkginfo
Requires-Dist: plover-stroke
Requires-Dist: plyer; "win32" in sys_platform
Requires-Dist: Pygments
Requires-Dist: pyobjc-core; "darwin" in sys_platform
Requires-Dist: pyobjc-framework-Cocoa; "darwin" in sys_platform
Requires-Dist: pyobjc-framework-Quartz; "darwin" in sys_platform
Requires-Dist: pyserial
Requires-Dist: python-xlib; "linux" in sys_platform or "bsd" in sys_platform
Requires-Dist: evdev; "linux" in sys_platform or "bsd" in sys_platform
Requires-Dist: packaging
Requires-Dist: psutil; "linux" in sys_platform or "bsd" in sys_platform
Requires-Dist: xkbcommon<1.1; "linux" in sys_platform or "bsd" in sys_platform
Requires-Dist: readme-renderer[md]
Requires-Dist: requests-cache
Requires-Dist: requests-futures
Requires-Dist: rtf_tokenize
Requires-Dist: setuptools
Requires-Dist: wcwidth
Provides-Extra: gui-qt
Requires-Dist: PySide6-Essentials; extra == "gui-qt"
Provides-Extra: log
Dynamic: download-url
Dynamic: home-page
Dynamic: license
Dynamic: license-file
Dynamic: provides-extra
Dynamic: requires-dist
Dynamic: summary
